README.md
setup.cfg
setup.py
distributions_ehman/Binomialdistribution.py
distributions_ehman/Gaussiandistribution.py
distributions_ehman/Generaldistribution.py
distributions_ehman/__init__.py
distributions_martinehman.egg-info/PKG-INFO
distributions_martinehman.egg-info/SOURCES.txt
distributions_martinehman.egg-info/dependency_links.txt
distributions_martinehman.egg-info/not-zip-safe
distributions_martinehman.egg-info/top_level.txt