Metadata-Version: 1.0
Name: distributions-martinehman
Version: 0.1
Summary: Gaussian distributions
Home-page: UNKNOWN
Author: Martin Ehman
Author-email: martinehman90@gmail.com
License: UNKNOWN
Platform: UNKNOWN
